rvic_convolution.cpython-35m-darwin.so
rvic/__init__.py
rvic/convert.py
rvic/convolution.py
rvic/parameters.py
rvic/version.py
rvic/core/__init__.py
rvic/core/aggregate.py
rvic/core/config.py
rvic/core/convert.py
rvic/core/convolution_wrapper.py
rvic/core/history.py
rvic/core/log.py
rvic/core/make_uh.py
rvic/core/multi_proc.py
rvic/core/param_file.py
rvic/core/plots.py
rvic/core/pycompat.py
rvic/core/read_forcing.py
rvic/core/remap.py
rvic/core/share.py
rvic/core/time_utility.py
rvic/core/utilities.py
rvic/core/variables.py
rvic/core/write.py
rvic-1.1.0.data/scripts/find_pour_points.py
rvic-1.1.0.data/scripts/fraction2domain.bash
rvic-1.1.0.data/scripts/rvic
rvic-1.1.0.dist-info/DESCRIPTION.rst
rvic-1.1.0.dist-info/METADATA
rvic-1.1.0.dist-info/RECORD
rvic-1.1.0.dist-info/WHEEL
rvic-1.1.0.dist-info/metadata.json
rvic-1.1.0.dist-info/top_level.txt
