Metadata-Version: 2.0
Name: rvic
Version: 1.1.0
Summary: The RVIC Streamflow Routing Model
Home-page: https://github.com/UW-Hydro/RVIC
Author: Joe Hamman
Author-email: jhamman1@uw.edu
License: UNKNOWN
Platform: UNKNOWN
Classifier: Development Status :: 4 - Beta
Classifier: License :: OSI Approved :: GNU General Public License v3 (GPLv3)
Classifier: Operating System :: OS Independent
Classifier: Intended Audience :: Science/Research
Classifier: Programming Language :: Python
Classifier: Programming Language :: Python :: 2
Classifier: Programming Language :: Python :: 2.7
Classifier: Programming Language :: Python :: 3
Classifier: Programming Language :: Python :: 3.4
Classifier: Programming Language :: Python :: 3.5
Classifier: Topic :: Scientific/Engineering
Requires-Dist: matplotlib (>=1.3.1)
Requires-Dist: netCDF4 (>=1.0.6)
Requires-Dist: numpy (>=1.8)
Requires-Dist: pandas (>=0.15.1)
Requires-Dist: scipy (>=0.13)
